twinkle_cli/__init__.py
twinkle_cli/_twinkle.py
twinkle_py-0.1.1.dist-info/LICENSE
twinkle_py-0.1.1.dist-info/METADATA
twinkle_py-0.1.1.dist-info/WHEEL
twinkle_py-0.1.1.dist-info/top_level.txt
twinkle_py-0.1.1.dist-info/RECORD
